nv_ingest_api/__init__.py
nv_ingest_api/interface/__init__.py
nv_ingest_api/interface/extract.py
nv_ingest_api/interface/mutate.py
nv_ingest_api/interface/store.py
nv_ingest_api/interface/transform.py
nv_ingest_api/interface/utility.py
nv_ingest_api/internal/__init__.py
nv_ingest_api/internal/enums/__init__.py
nv_ingest_api/internal/enums/common.py
nv_ingest_api/internal/extract/__init__.py
nv_ingest_api/internal/extract/audio/__init__.py
nv_ingest_api/internal/extract/audio/audio_extraction.py
nv_ingest_api/internal/extract/docx/__init__.py
nv_ingest_api/internal/extract/docx/docx_extractor.py
nv_ingest_api/internal/extract/docx/engines/__init__.py
nv_ingest_api/internal/extract/docx/engines/docxreader_helpers/__init__.py
nv_ingest_api/internal/extract/docx/engines/docxreader_helpers/docx_helper.py
nv_ingest_api/internal/extract/docx/engines/docxreader_helpers/docxreader.py
nv_ingest_api/internal/extract/html/__init__.py
nv_ingest_api/internal/extract/html/html_extractor.py
nv_ingest_api/internal/extract/image/__init__.py
nv_ingest_api/internal/extract/image/chart_extractor.py
nv_ingest_api/internal/extract/image/image_extractor.py
nv_ingest_api/internal/extract/image/infographic_extractor.py
nv_ingest_api/internal/extract/image/table_extractor.py
nv_ingest_api/internal/extract/image/image_helpers/__init__.py
nv_ingest_api/internal/extract/image/image_helpers/common.py
nv_ingest_api/internal/extract/pdf/__init__.py
nv_ingest_api/internal/extract/pdf/pdf_extractor.py
nv_ingest_api/internal/extract/pdf/engines/__init__.py
nv_ingest_api/internal/extract/pdf/engines/adobe.py
nv_ingest_api/internal/extract/pdf/engines/llama.py
nv_ingest_api/internal/extract/pdf/engines/nemoretriever.py
nv_ingest_api/internal/extract/pdf/engines/pdfium.py
nv_ingest_api/internal/extract/pdf/engines/tika.py
nv_ingest_api/internal/extract/pdf/engines/unstructured_io.py
nv_ingest_api/internal/extract/pdf/engines/pdf_helpers/__init__.py
nv_ingest_api/internal/extract/pptx/__init__.py
nv_ingest_api-25.9.0.dist-info/licenses/LICENSE
nv_ingest_api-25.9.0.dist-info/METADATA
nv_ingest_api-25.9.0.dist-info/WHEEL
nv_ingest_api-25.9.0.dist-info/top_level.txt
nv_ingest_api-25.9.0.dist-info/RECORD
