Metadata-Version: 2.4
Name: nv-ingest-api
Version: 25.9.0
Summary: Python module with core document ingestion functions.
Author-email: Jeremy Dyer <jdyer@nvidia.com>
License:                                  Apache License
Project-URL: homepage, https://github.com/NVIDIA/nv-ingest
Project-URL: repository, https://github.com/NVIDIA/nv-ingest
Project-URL: documentation, https://docs.nvidia.com/nv-ingest
Classifier: Programming Language :: Python :: 3
Classifier: License :: OSI Approved :: MIT License
Classifier: Operating System :: OS Independent
License-File: LICENSE
Requires-Dist: backoff==2.2.1
Requires-Dist: pandas>=2.0
Requires-Dist: pydantic>2.0.0
Requires-Dist: pydantic-settings>2.0.0
Requires-Dist: tritonclient
Dynamic: license-file
